zope/browsermenu/README.txt
zope/browsermenu/__init__.py
zope/browsermenu/configure.zcml
zope/browsermenu/field.py
zope/browsermenu/interfaces.py
zope/browsermenu/menu.py
zope/browsermenu/meta.zcml
zope/browsermenu/metaconfigure.py
zope/browsermenu/metadirectives.py
zope/browsermenu/tests/__init__.py
zope/browsermenu/tests/addmenuitems.zcml
zope/browsermenu/tests/menus-permissions.zcml
zope/browsermenu/tests/menus.zcml
zope/browsermenu/tests/test_addMenuItem.py
zope/browsermenu/tests/test_directives.py
zope/browsermenu/tests/test_fields.py
zope/browsermenu/tests/test_menu.py
zope/browsermenu/tests/test_menudirectives.py
zope_browsermenu-6.0.dist-info/licenses/LICENSE.txt
zope_browsermenu-6.0.dist-info/METADATA
zope_browsermenu-6.0.dist-info/WHEEL
zope_browsermenu-6.0.dist-info/top_level.txt
zope_browsermenu-6.0.dist-info/RECORD
